safe_ase/__init__.py
safe_ase/safe_add_adsorbate.py
safe_ase/safe_euler_rotation.py
safe_ase/safe_remove_atom_by_index.py
safe_ase/safe_structure.py
safe_ase-0.0.2.dist-info/METADATA
safe_ase-0.0.2.dist-info/WHEEL
safe_ase-0.0.2.dist-info/top_level.txt
safe_ase-0.0.2.dist-info/RECORD
