Metadata-Version: 2.1
Name: safe-ase
Version: 0.0.2
Summary: safe_ase
Author: Roberto Rousse
Author-email: <roberto.rousse@gmail.com>
Keywords: python,first package
Classifier: Development Status :: 3 - Alpha
Classifier: Programming Language :: Python :: 3
Requires-Dist: ase
